awsup/__init__.py
awsup/cli.py
awsup/config.py
awsup/production_deployer.py
awsup/profile_manager.py
awsup/validators.py
awsup/managers/__init__.py
awsup/managers/acm.py
awsup/managers/base.py
awsup/managers/cloudfront.py
awsup/managers/route53.py
awsup/managers/s3.py
awsup/templates/default-index.html
awsup/utils/__init__.py
awsup/utils/interactive.py
awsup-2.3.3.dist-info/licenses/LICENSE
infrastructure/cdk/website_stack.py
awsup-2.3.3.dist-info/METADATA
awsup-2.3.3.dist-info/WHEEL
awsup-2.3.3.dist-info/entry_points.txt
awsup-2.3.3.dist-info/top_level.txt
awsup-2.3.3.dist-info/RECORD
