Metadata-Version: 2.4
Name: awsup
Version: 2.3.3
Summary: 🚀 AWSUP - Lightning-fast AWS static website deployment
Author-email: Ahmed Akram <eng.akramovic@gmail.com>
License: MIT License
Project-URL: Homepage, https://github.com/Akramovic1/aws-website-quick-deployer
Project-URL: Repository, https://github.com/Akramovic1/aws-website-quick-deployer
Project-URL: Issues, https://github.com/Akramovic1/aws-website-quick-deployer/issues
Project-URL: Documentation, https://github.com/Akramovic1/aws-website-quick-deployer#readme
Keywords: aws,s3,cloudfront,route53,website,deployment,static-site
Classifier: Development Status :: 5 - Production/Stable
Classifier: Environment :: Console
Classifier: Intended Audience :: Developers
Classifier: License :: OSI Approved :: MIT License
Classifier: Operating System :: OS Independent
Classifier: Programming Language :: Python :: 3
Classifier: Programming Language :: Python :: 3.8
Classifier: Programming Language :: Python :: 3.9
Classifier: Programming Language :: Python :: 3.10
Classifier: Programming Language :: Python :: 3.11
Classifier: Programming Language :: Python :: 3.12
Classifier: Topic :: Internet :: WWW/HTTP
Classifier: Topic :: Software Development :: Build Tools
Classifier: Topic :: System :: Installation/Setup
Classifier: Topic :: Utilities
Requires-Python: >=3.8
License-File: LICENSE
Requires-Dist: boto3>=1.34.0
Requires-Dist: botocore>=1.34.0
Requires-Dist: pydantic>=2.0.0
Requires-Dist: click>=8.1.0
Requires-Dist: rich>=13.0.0
Requires-Dist: jinja2>=3.1.0
Requires-Dist: questionary>=2.0.0
Provides-Extra: dev
Requires-Dist: pytest>=7.4.0; extra == "dev"
Requires-Dist: pytest-cov>=4.1.0; extra == "dev"
Requires-Dist: pytest-mock>=3.11.0; extra == "dev"
Requires-Dist: black>=23.0.0; extra == "dev"
Requires-Dist: flake8>=6.0.0; extra == "dev"
Requires-Dist: mypy>=1.5.0; extra == "dev"
Requires-Dist: bandit>=1.7.0; extra == "dev"
Provides-Extra: cdk
Requires-Dist: aws-cdk-lib>=2.100.0; extra == "cdk"
Requires-Dist: constructs>=10.0.0; extra == "cdk"
Dynamic: license-file
